MarketDataManager/__init__.py
MarketDataManager/client.py
tests/__init__.py
tests/test_client .py
MarketDataManager-0.2.dist-info/LICENSE
MarketDataManager-0.2.dist-info/METADATA
MarketDataManager-0.2.dist-info/WHEEL
MarketDataManager-0.2.dist-info/top_level.txt
MarketDataManager-0.2.dist-info/RECORD
