Metadata-Version: 2.1
Name: MarketDataManager
Version: 0.2
Summary: A client library to manage a postgresSQL database of financial market data, using a docker containerized api.
Home-page: https://github.com/anthonyb8/MarketData
Author: Anthony Baxter
Author-email: anthonybaxter819@gmail.com
License: Apache 2.0
Keywords: marketdata,postgresSQL,financial,docker
Platform: UNKNOWN
Classifier: Development Status :: 3 - Alpha
Classifier: License :: OSI Approved :: Apache Software License
Classifier: Programming Language :: Python 
Classifier: Programming Language :: Python :: 3
Requires-Python: >=3.10
Requires-Dist: certifi (>=2023.7.22)
Requires-Dist: charset-normalizer (>=3.2.0)
Requires-Dist: requests (>=2.31.0)
Requires-Dist: urllib3 (>=2.0.4)
